{
 "PlatformInfo": {
  "Platform": {
   "Name": "Windows",
   "BasePlatform": "Windows",
   "Generator": "2024.1.2.8725"
  },
  "RootPaths": {
   "ProjectRoot": "../..",
   "SourceFilesRoot": "../../.cache",
   "SoundBanksRoot": ".",
   "ExternalSourcesInputFile": "",
   "ExternalSourcesOutputRoot": "."
  },
  "DefaultAlign": "16",
  "Settings": {
   "AutoSoundBankDefinition": "false",
   "CopyLooseStreamedMediaFiles": "true",
   "SubFoldersForGeneratedFiles": "false",
   "RemoveUnusedGeneratedFiles": "true",
   "SourceControlGeneratedFiles": "false",
   "GenerateHeaderFile": "true",
   "GenerateContentTxtFile": "true",
   "GenerateMetadataXML": "false",
   "GenerateMetadataJSON": "true",
   "GenerateAllBanksMetadata": "true",
   "GeneratePerBankMetadata": "false",
   "UseSoundBankNames": "true",
   "AllowExceedingMaxSize": "false",
   "MaxAttenuationInfo": "true",
   "EstimatedDurationInfo": "true",
   "PrintObjectGuid": "true",
   "PrintObjectPath": "true",
   "PrintObjectColor": "true"
  },
  "FileHash": "{330B4D2D-638A-3AB2-84E2-BA90AC37D3E7}"
 }
}